ovadare/__init__.py
ovadare/agents/__init__.py
ovadare/agents/agent.py
ovadare/agents/agent_interface.py
ovadare/agents/agent_registry.py
ovadare/agents/agent_sdk.py
ovadare/communication/__init__.py
ovadare/communication/api_endpoints.py
ovadare/communication/security.py
ovadare/conflicts/__init__.py
ovadare/conflicts/conflict.py
ovadare/conflicts/conflict_classifier.py
ovadare/conflicts/conflict_detector.py
ovadare/conflicts/resolution.py
ovadare/conflicts/resolution_engine.py
ovadare/escalation/__init__.py
ovadare/escalation/ai_assistant.py
ovadare/escalation/escalation_manager.py
ovadare/escalation/human_interface.py
ovadare/feedback/__init__.py
ovadare/feedback/adaptive_learning.py
ovadare/feedback/feedback_loop.py
ovadare/feedback/feedback_manager.py
ovadare/feedback/policy_adjustment.py
ovadare/monitoring/__init__.py
ovadare/monitoring/analytics.py
ovadare/monitoring/dashboards.py
ovadare/monitoring/monitoring_service.py
ovadare/monitoring/reporting.py
ovadare/policies/__init__.py
ovadare/policies/dynamic_policy_loader.py
ovadare/policies/dynamic_policy_manager.py
ovadare/policies/policy.py
ovadare/policies/policy_manager.py
ovadare/policies/policy_rules.py
ovadare/utils/__init__.py
ovadare/utils/configuration.py
ovadare/utils/logging_config.py
ovadare/utils/secrets_manager.py
ovadare-0.1.4.dist-info/LICENSE
ovadare-0.1.4.dist-info/METADATA
ovadare-0.1.4.dist-info/WHEEL
ovadare-0.1.4.dist-info/top_level.txt
ovadare-0.1.4.dist-info/RECORD
