Metadata-Version: 2.1
Name: ovadare
Version: 0.1.4
Summary: A framework for conflict detection and resolution in multi-agent systems.
Home-page: https://github.com/nospecs/ovadare
Author: Oren Mukades
Author-email: ai@ovadare.com
License: MIT
Classifier: Programming Language :: Python :: 3
Classifier: License :: OSI Approved :: MIT License
Classifier: Operating System :: OS Independent
Requires-Python: >=3.7
License-File: LICENSE
Requires-Dist: autogen>=0.2.0
Provides-Extra: dev
Requires-Dist: sphinx>=5.3.0; extra == "dev"
Requires-Dist: sphinx_rtd_theme>=1.2.0; extra == "dev"
